[
  {
    "id": 1,
    "title": "소년이 온다",
    "description": "2014년 만해문학상, 2017년 이탈리아 말라파르테 문학상을 수상하고 전세계 20여개국에 번역 출간되며 세계를 사로잡은 우리 시대의 소설 <소년이 온다>",
    "author": "한강",
    "price": 13500,
    "stock": 50,
    "totalSales": 300
  },
  {
    "id": 2,
    "title": "채식주의자",
    "description": "2016년 인터내셔널 부커상을 수상하며 한국문학의 입지를 한단계 확장시킨 한강의 장편소설 『채식주의자』를 15년 만에 새로운 장정으로 선보인다.",
    "author": "한강",
    "price": 13500,
    "stock": 5,
    "totalSales": 100
  },
  {
    "id": 3,
    "title": "어른의 행복은 조용하다",
    "description": "《1cm 다이빙》, 《홈 in 홈》으로 많은 사랑을 받았던 에세이스트 태수가 2년 만의 신작 《어른의 행복은 조용하다》로 돌아왔다.",
    "author": "태수",
    "price": 16200,
    "stock": 5,
    "totalSales": 100
  },
  {
    "id": 4,
    "title": "일의 감각",
    "description": "한 호에 하나씩, 균형 잡힌 브랜드를 선정하여 그 철학과 감성, 이야기를 소개하는 매거진 《B》의 발행인 조수용의 에세이 《일의 감각》이 출간되었다.",
    "author": "조수용",
    "price": 19800,
    "stock": 50,
    "totalSales": 0
  },
  {
    "id": 5,
    "title": "모순",
    "description": "양귀자 소설의 힘을 보여준 베스트셀러 『모순』.",
    "author": "양귀자",
    "price": 11700,
    "stock": 0,
    "totalSales": 100
  },
  {
    "id": 6,
    "title": "달러구트 꿈 백화점 1",
    "description": "잠들어야만 입장 가능한 꿈 백화점에서 일어나는 비밀스럽고도 기묘하며 가슴 뭉클한 판타지 소설",
    "author": "이미예",
    "price": 12400,
    "stock": 0,
    "totalSales": 100
  },
  {
    "id": 7,
    "title": "달러구트 꿈 백화점 2",
    "description": "잠들어야만 입장 가능한 꿈 백화점에서 일어나는 비밀스럽고도 기묘하며 가슴 뭉클한 판타지 소설",
    "author": "이미예",
    "price": 12400,
    "stock": 100,
    "totalSales": 200
  },
  {
    "id": 8,
    "title": "찬란한 날들",
    "description": "어두움 속 저 멀리 작고 희미하게 빛나는 반딧불을 닮은 7편의 이야기 한소은 소설집 『찬란한 날들』",
    "author": "한소은",
    "price": 15300,
    "stock": 50,
    "totalSales": 20
  },
  {
    "id": 9,
    "title": "탕비실",
    "description": "150만 독자가 사랑한 《달러구트 꿈 백화점》 이미예 작가가 이번에는 《탕비실》로 독자들을 찾았다.",
    "author": "이미예",
    "price": 12600,
    "stock": 5,
    "totalSales": 100
  },
  {
    "id": 10,
    "title": "튜브",
    "description": "100만부 베스트셀러 『아몬드』 작가 손원평의 빛나는 신작, 모두의 인생을 향해 보내는 강력한 응원",
    "author": "손원평",
    "price": 13500,
    "stock": 15,
    "totalSales": 10
  },
  {
    "id": 11,
    "title": "아몬드",
    "description": "『아몬드』는 ‘감정을 느끼지 못하는 소년’ 윤재가 세상에 걸음을 내딛는 이야기로, 청소년부터 성인에 이르기까지 전연령대 독자의 꾸준한 사랑을 받아왔다.",
    "author": "손원평",
    "price": 15120,
    "stock": 7,
    "totalSales": 150
  },
  {
    "id": 12,
    "title": "순례 주택",
    "description": "행복해지려고 노력하는 모든 이에게 전하는 유은실의 단.짠.단.짠 위로",
    "author": "유은실",
    "price": 13500,
    "stock": 11,
    "totalSales": 25
  },
  {
    "id": 13,
    "title": "천문학자는 별을 보지 않는다",
    "description": "창백한 푸른 점 속 천문학자가 일상을 살아가며, 우주를 사랑하는 법",
    "author": "심채경",
    "price": 13500,
    "stock": 5,
    "totalSales": 25
  },
  {
    "id": 14,
    "title": "유럽도시기행 1",
    "description": "아테네, 로마, 이스탄불, 파리 편",
    "author": "유시민",
    "price": 14850,
    "stock": 0,
    "totalSales": 53
  },
  {
    "id": 15,
    "title": "유럽도시기행 2",
    "description": "빈, 부다페스트, 프라하, 드레스덴 편",
    "author": "유시민",
    "price": 15750,
    "stock": 5,
    "totalSales": 25
  },
  {
    "id": 16,
    "title": "작별하지 않는다",
    "description": "2024 노벨문학상 수상 작가 한강",
    "author": "한강",
    "price": 15120,
    "stock": 5,
    "totalSales": 100
  },
  {
    "id": 17,
    "title": "흰",
    "description": "2024 노벨문학상 수상 작가 한강",
    "author": "한강",
    "price": 13050,
    "stock": 5,
    "totalSales": 100
  },
  {
    "id": 18,
    "title": "서랍에 저녁을 넣어 두었다",
    "description": "2024 노벨문학상 수상 작가 한강",
    "author": "한강",
    "price": 13500,
    "stock": 5,
    "totalSales": 100
  },
  {
    "id": 19,
    "title": "희랍어 시간",
    "description": "2024 노벨문학상 수상 작가 한강",
    "author": "한강",
    "price": 13500,
    "stock": 5,
    "totalSales": 100
  },
  {
    "id": 20,
    "title": "여수의 사랑",
    "description": "2024 노벨문학상 수상 작가 한강",
    "author": "한강",
    "price": 13500,
    "stock": 5,
    "totalSales": 100
  },
  {
    "id": 21,
    "title": "한강 스페셜 에디션",
    "description": "한강 스페셜 에디션 모음",
    "author": "한강",
    "price": 13500,
    "stock": 5,
    "totalSales": 100
  },
  {
    "id": 22,
    "title": "검은 사슴",
    "description": "2024 노벨문학상 수상 작가 한강",
    "author": "한강",
    "price": 13500,
    "stock": 5,
    "totalSales": 100
  },
  {
    "id": 23,
    "title": "그대의 차가운 손",
    "description": "2024 노벨문학상 수상 작가 한강",
    "author": "한강",
    "price": 13500,
    "stock": 5,
    "totalSales": 100
  },
  {
    "id": 24,
    "title": "채식주의자(큰글자도서)",
    "description": "2024 노벨문학상 수상 작가 한강",
    "author": "한강",
    "price": 13500,
    "stock": 5,
    "totalSales": 100
  }
]
